{
  "metadata": {
    "category": "headphones",
    "total_products": 21,
    "canada_verified_count": 17,
    "not_available_count": 4,
    "in_stock_count": 15
  },
  "purchase_paths": [
    {
      "canonical_product_id": "p_001",
      "canonical_product_name": "Sony WH-1000XM6",
      "brand": "Sony",
      "retailer": "walmart.ca",
      "product_url": "https://www.walmart.ca/en/ip/Sony-WH-1000XM6-Wireless-Noise-Canceling-Headphones-30-Hour-Battery-Adaptive-NC-Optimizer-Platinum-Silver/5PUL4Z1FS59L",
      "price_cad": 479.0,
      "in_stock": true,
      "canada_verified": true,
      "canadian_company": false,
      "made_in_canada": false,
      "notes": ""
    },
    {
      "canonical_product_id": "p_002",
      "canonical_product_name": "Sony WH-1000XM4 Wireless",
      "brand": "Sony",
      "retailer": "electronics.sony.ca",
      "product_url": "https://electronics.sony.ca/en/audio/headphones/all-headphones/p/wh1000xm4-b",
      "price_cad": 429.99,
      "in_stock": true,
      "canada_verified": true,
      "canadian_company": false,
      "made_in_canada": false,
      "notes": ""
    },
    {
      "canonical_product_id": "p_003",
      "canonical_product_name": "Anker Soundcore Space Q45 Wireless",
      "brand": "Anker",
      "retailer": "soundcore.com",
      "product_url": "https://www.soundcore.com/ca/products/space-q45-a3040011",
      "price_cad": 199.99,
      "in_stock": true,
      "canada_verified": true,
      "canadian_company": false,
      "made_in_canada": false,
      "notes": ""
    },
    {
      "canonical_product_id": "p_004",
      "canonical_product_name": "Anker Soundcore Life Q20 2024",
      "brand": "Anker",
      "retailer": "soundcore.com/ca",
      "product_url": "https://www.soundcore.com/ca/products/a3025",
      "price_cad": 79.99,
      "in_stock": true,
      "canada_verified": true,
      "canadian_company": false,
      "made_in_canada": false,
      "notes": ""
    },
    {
      "canonical_product_id": "p_005",
      "canonical_product_name": "Anker Soundcore Life Q30 Wireless",
      "brand": "Anker",
      "retailer": "Amazon.ca",
      "product_url": "https://www.amazon.ca/dp/B08HMWZBXC",
      "price_cad": 66.49,
      "in_stock": true,
      "canada_verified": true,
      "canadian_company": false,
      "made_in_canada": false,
      "notes": ""
    },
    {
      "canonical_product_id": "p_006",
      "canonical_product_name": "Sennheiser HDB 630",
      "brand": "Sennheiser",
      "retailer": "bestbuy.ca",
      "product_url": "https://www.bestbuy.ca/en-ca/product/sennheiser-hdb-630-wireless-over-ear-headphones-black/19495516",
      "price_cad": 699.95,
      "in_stock": true,
      "canada_verified": false,
      "canadian_company": false,
      "made_in_canada": false,
      "notes": "URL validation failed (non-200 or unreachable)"
    },
    {
      "canonical_product_id": "p_007",
      "canonical_product_name": "JBL Tune 760NC",
      "brand": "JBL",
      "retailer": "JBL Canada",
      "product_url": "https://www.jblcanada.ca/product/jbl-tune-760nc-over-ear-headphones/",
      "price_cad": 103.62,
      "in_stock": true,
      "canada_verified": false,
      "canadian_company": false,
      "made_in_canada": false,
      "notes": "URL validation failed (non-200 or unreachable)"
    },
    {
      "canonical_product_id": "p_008",
      "canonical_product_name": "Apple AirPods Max (2nd gen)",
      "brand": "Apple",
      "retailer": "Apple Store Canada",
      "product_url": "https://www.apple.com/ca/shop/buy-airpods/airpods-max-2",
      "price_cad": 799.0,
      "in_stock": true,
      "canada_verified": true,
      "canadian_company": false,
      "made_in_canada": false,
      "notes": ""
    },
    {
      "canonical_product_id": "p_009",
      "canonical_product_name": "Edifier W820NB Plus",
      "brand": "Edifier",
      "retailer": "staples.ca",
      "product_url": "https://www.staples.ca/products/3172102-en-edifier-w820nb-plus-wireless-over-ear-headphones-ldac-hi-res-49db-anc-bt-61-multipoint-spatial-sound-with-fast-charging-gray",
      "price_cad": 129.99,
      "in_stock": true,
      "canada_verified": false,
      "canadian_company": false,
      "made_in_canada": false,
      "notes": "URL validation failed (non-200 or unreachable)"
    },
    {
      "canonical_product_id": "p_010",
      "canonical_product_name": "JBL Tour One M3",
      "brand": "JBL",
      "retailer": "ca.jbl.com",
      "product_url": "https://ca.jbl.com/en_CA/TOUR-ONE-M3.html?dwvar_TOUR-ONE-M3_color=Black-AM-Current",
      "price_cad": 499.98,
      "in_stock": true,
      "canada_verified": true,
      "canadian_company": false,
      "made_in_canada": false,
      "notes": ""
    },
    {
      "canonical_product_id": "p_011",
      "canonical_product_name": "Bose QuietComfort Headphones",
      "brand": "Bose",
      "retailer": "bose.ca",
      "product_url": "https://www.bose.ca/en/p/headphones/quietcomfort-acoustic-noise-cancelling-headphones/QC-HEADPHONEARN-TWBL-WW.html",
      "price_cad": 479.0,
      "in_stock": true,
      "canada_verified": true,
      "canadian_company": false,
      "made_in_canada": false,
      "notes": ""
    },
    {
      "canonical_product_id": "p_012",
      "canonical_product_name": "Bowers & Wilkins PX8",
      "brand": "Bowers & Wilkins",
      "retailer": "bowerswilkins.com",
      "product_url": "https://www.bowerswilkins.com/en-ca/product/over-ear-headphones/px8/300494-01-00-308.html",
      "price_cad": 949.0,
      "in_stock": true,
      "canada_verified": true,
      "canadian_company": false,
      "made_in_canada": false,
      "notes": "Price $949.0 outside expected range $50-$800"
    },
    {
      "canonical_product_id": "p_013",
      "canonical_product_name": "JLab JBuds Lux ANC",
      "brand": "JLab",
      "retailer": "jlab.com",
      "product_url": "https://www.jlab.com/en-ca/products/jbuds-lux-anc-headphones-graphite",
      "price_cad": 79.99,
      "in_stock": false,
      "canada_verified": true,
      "canadian_company": false,
      "made_in_canada": false,
      "notes": ""
    },
    {
      "canonical_product_id": "p_014",
      "canonical_product_name": "Marshall Monitor III ANC",
      "brand": "Marshall",
      "retailer": "marshall.com",
      "product_url": "https://www.marshall.com/ca/en/product/monitor-iii-anc?pid=1006861",
      "price_cad": 499.99,
      "in_stock": true,
      "canada_verified": true,
      "canadian_company": false,
      "made_in_canada": false,
      "notes": ""
    },
    {
      "canonical_product_id": "p_015",
      "canonical_product_name": "Puro Sound Labs PuroQuiet",
      "brand": "Puro Sound Labs",
      "retailer": "purosound.com",
      "product_url": "https://purosound.com/en-ca/collections/puroquiets/products/puroquiet-over-ear-active-noise-cancelling-headphones",
      "price_cad": 179.0,
      "in_stock": false,
      "canada_verified": true,
      "canadian_company": false,
      "made_in_canada": false,
      "notes": ""
    },
    {
      "canonical_product_id": "p_016",
      "canonical_product_name": "Sennheiser MOMENTUM 4 Wireless",
      "brand": "Sennheiser",
      "retailer": "ca.sennheiser-hearing.com",
      "product_url": "https://ca.sennheiser-hearing.com/products/momentum-4-wireless",
      "price_cad": 279.95,
      "in_stock": true,
      "canada_verified": true,
      "canadian_company": false,
      "made_in_canada": false,
      "notes": ""
    },
    {
      "canonical_product_id": "p_017",
      "canonical_product_name": "Sennheiser ACCENTUM Plus",
      "brand": "Sennheiser",
      "retailer": "ca.sennheiser-hearing.com",
      "product_url": "https://ca.sennheiser-hearing.com/products/accentum-plus",
      "price_cad": 329.95,
      "in_stock": true,
      "canada_verified": true,
      "canadian_company": false,
      "made_in_canada": false,
      "notes": ""
    },
    {
      "canonical_product_id": "p_018",
      "canonical_product_name": "Sony WH-CH720N",
      "brand": "Sony",
      "retailer": "walmart.ca",
      "product_url": "https://www.walmart.ca/en/ip/Sony-WH-CH720N-Wireless-Noise-Cancelling-Headphone/6000206405303?athbdg=L1102&classType=REGULAR",
      "price_cad": 169.96,
      "in_stock": true,
      "canada_verified": true,
      "canadian_company": false,
      "made_in_canada": false,
      "notes": ""
    },
    {
      "canonical_product_id": "p_019",
      "canonical_product_name": "Bose QuietComfort Ultra Headphones",
      "brand": "Bose",
      "retailer": "bose.ca",
      "product_url": "https://www.bose.ca/en/p/headphones/bose-quietcomfort-ultra-headphones/QCUH-HEADPHONEARN.html",
      "price_cad": 549.0,
      "in_stock": true,
      "canada_verified": true,
      "canadian_company": false,
      "made_in_canada": false,
      "notes": ""
    },
    {
      "canonical_product_id": "p_020",
      "canonical_product_name": "1More Sonoflow Pro HQ51",
      "brand": "1More",
      "retailer": "bestbuy.ca",
      "product_url": "https://www.bestbuy.ca/en-ca/product/1more-sonoflow-pro-noise-cancelling-headphones-hq51-over-ear-bluetooth-headphones-black/19625887",
      "price_cad": null,
      "in_stock": true,
      "canada_verified": false,
      "canadian_company": false,
      "made_in_canada": false,
      "notes": "URL validation failed (non-200 or unreachable)"
    },
    {
      "canonical_product_id": "p_021",
      "canonical_product_name": "Soundpeats Cove Pro",
      "brand": "Soundpeats",
      "retailer": "soundpeats.com",
      "product_url": "https://soundpeats.com/en-ca/products/cove-pro-eu",
      "price_cad": 107.07,
      "in_stock": true,
      "canada_verified": true,
      "canadian_company": false,
      "made_in_canada": false,
      "notes": ""
    },
    {
      "canonical_product_id": "p_022",
      "canonical_product_name": "PSB M4U 8 MKII Wireless ANC Headphones",
      "brand": "PSB Speakers",
      "retailer": "psbspeakers.com/ca",
      "product_url": "https://www.psbspeakers.com/ca/headphones/m4u-8-headphone",
      "price_cad": 399.0,
      "in_stock": true,
      "canada_verified": true,
      "canadian_company": true,
      "made_in_canada": false,
      "reviewer_backed": false,
      "notes": "Canadian brand product (PSB Speakers, Pickering ON). Not reviewer-backed."
    }
  ],
  "canadian_brands": [
    {
      "brand_name": "PSB Speakers",
      "headquarters_location": "Pickering, Ontario",
      "canadian_company": true,
      "made_in_canada": false,
      "notes": "Canadian loudspeaker company founded 1972, designs headphones in Canada."
    }
  ]
}